ipannotoryous/__init__.py
ipannotoryous/_frontend.py
ipannotoryous/_version.py
ipannotoryous/annotorius.py
ipannotoryous/labextension/package.json
ipannotoryous/labextension/static/212.2c83c9f0b7e501b2af87.js
ipannotoryous/labextension/static/212.2c83c9f0b7e501b2af87.js.LICENSE.txt
ipannotoryous/labextension/static/446.db7b9da57530b09abce6.js
ipannotoryous/labextension/static/480.0f0302e5e47f3104400e.js
ipannotoryous/labextension/static/568.98565b4ba6ec80d221eb.js
ipannotoryous/labextension/static/841.4f842058d8f7a3a7b721.js
ipannotoryous/labextension/static/remoteEntry.596ead46dba64352b500.js
ipannotoryous/labextension/static/style.js
ipannotoryous/nbextension/__init__.py
ipannotoryous/nbextension/static/extension.js
ipannotoryous/nbextension/static/index.js
ipannotoryous/nbextension/static/index.js.map
ipannotoryous/tests/__init__.py
ipannotoryous/tests/conftest.py
ipannotoryous/tests/test_annotorious.py
ipannotoryous/tests/test_nbextension_path.py
ipannotoryous-1.0.0.post1.data/data/etc/jupyter/nbconfig/notebook.d/ipannotoryous.json
ipannotoryous-1.0.0.post1.data/data/share/jupyter/labextensions/ipannotoryous/package.json
ipannotoryous-1.0.0.post1.data/data/share/jupyter/labextensions/ipannotoryous/static/212.2c83c9f0b7e501b2af87.js
ipannotoryous-1.0.0.post1.data/data/share/jupyter/labextensions/ipannotoryous/static/212.2c83c9f0b7e501b2af87.js.LICENSE.txt
ipannotoryous-1.0.0.post1.data/data/share/jupyter/labextensions/ipannotoryous/static/446.db7b9da57530b09abce6.js
ipannotoryous-1.0.0.post1.data/data/share/jupyter/labextensions/ipannotoryous/static/480.0f0302e5e47f3104400e.js
ipannotoryous-1.0.0.post1.data/data/share/jupyter/labextensions/ipannotoryous/static/568.98565b4ba6ec80d221eb.js
ipannotoryous-1.0.0.post1.data/data/share/jupyter/labextensions/ipannotoryous/static/841.4f842058d8f7a3a7b721.js
ipannotoryous-1.0.0.post1.data/data/share/jupyter/labextensions/ipannotoryous/static/remoteEntry.596ead46dba64352b500.js
ipannotoryous-1.0.0.post1.dist-info/LICENSE.txt
ipannotoryous-1.0.0.post1.dist-info/METADATA
ipannotoryous-1.0.0.post1.dist-info/WHEEL
ipannotoryous-1.0.0.post1.dist-info/top_level.txt
ipannotoryous-1.0.0.post1.dist-info/RECORD
