Metadata-Version: 2.1
Name: ipannotoryous
Version: 1.0.0.post1
Summary: A annotation Jupyter Widget based on Annotorius.
Home-page: https://github.com/fcollonval/ipannotoryous
Author: ARIADNEXT
Author-email: fcollonval@gmail.com
License: BSD
Keywords: Jupyter,Widgets,IPython
Platform: Linux
Platform: Mac OS X
Platform: Windows
Classifier: Intended Audience :: Developers
Classifier: Intended Audience :: Science/Research
Classifier: License :: OSI Approved :: BSD License
Classifier: Programming Language :: Python
Classifier: Programming Language :: Python :: 3
Classifier: Programming Language :: Python :: 3.6
Classifier: Programming Language :: Python :: 3.7
Classifier: Programming Language :: Python :: 3.8
Classifier: Programming Language :: Python :: 3.9
Classifier: Framework :: Jupyter
Requires-Python: >=3.6
Requires-Dist: ipywidgets (>=7.0.0)
Provides-Extra: docs
Requires-Dist: sphinx (>=1.5) ; extra == 'docs'
Requires-Dist: recommonmark ; extra == 'docs'
Requires-Dist: sphinx-rtd-theme ; extra == 'docs'
Requires-Dist: nbsphinx (<0.4.0,>=0.2.13) ; extra == 'docs'
Requires-Dist: jupyter-sphinx ; extra == 'docs'
Requires-Dist: nbsphinx-link ; extra == 'docs'
Requires-Dist: pytest-check-links ; extra == 'docs'
Requires-Dist: pypandoc ; extra == 'docs'
Provides-Extra: examples
Provides-Extra: test
Requires-Dist: pytest (>=4.6) ; extra == 'test'
Requires-Dist: pytest-asyncio ; extra == 'test'
Requires-Dist: pytest-cov ; extra == 'test'
Requires-Dist: nbval ; extra == 'test'
